LICENSE
MANIFEST.in
setup.cfg
setup.py
okfrontpanel/__init__.py
okfrontpanel/fp.py
okfrontpanel/wrapper_build.py
pyOKFrontPanel.egg-info/PKG-INFO
pyOKFrontPanel.egg-info/SOURCES.txt
pyOKFrontPanel.egg-info/dependency_links.txt
pyOKFrontPanel.egg-info/not-zip-safe
pyOKFrontPanel.egg-info/requires.txt
pyOKFrontPanel.egg-info/top_level.txt