Metadata-Version: 1.1
Name: pyOKFrontPanel
Version: 4.5.6a3
Summary: Python CFFI wrapper for the Opal Kelly FrontPanel FPGA interface
Home-page: https://github.com/Ulm-IQO/pyOKFrontPanel
Author: Qudi developers
Author-email: qudi@uni-ulm.de
License: MIT
Download-URL: https://github.com/Ulm-IQO/pyOKFrontPanel/archive/v4.5.6a3.tar.gz
Keywords: Opal Kelly FPGA FrontPanel
Platform: UNKNOWN
Classifier: Development Status :: 3 - Alpha
Classifier: License :: OSI Approved :: MIT License
Classifier: Programming Language :: Python
Classifier: Programming Language :: Python :: 3
Classifier: Operating System :: POSIX :: Linux
Classifier: Operating System :: Microsoft :: Windows
